ltp_server/__init__.py
ltp_server/client.py
ltp_server/config.yml
ltp_server/server.py
ltp_server-0.2.1.dist-info/LICENSE
ltp_server-0.2.1.dist-info/METADATA
ltp_server-0.2.1.dist-info/WHEEL
ltp_server-0.2.1.dist-info/entry_points.txt
ltp_server-0.2.1.dist-info/top_level.txt
ltp_server-0.2.1.dist-info/RECORD
