Metadata-Version: 2.1
Name: ltp-server
Version: 0.2.1
Summary: a simple LTP service implemented in Python based on FastAPI
Home-page: https://github.com/smilelight/ltp_server
Author: lightsmile
Author-email: iamlightsmile@gmail.com
License: MIT
Platform: UNKNOWN
Classifier: Development Status :: 4 - Beta
Classifier: Operating System :: OS Independent
Classifier: Intended Audience :: Developers
Classifier: License :: OSI Approved :: BSD License
Classifier: Programming Language :: Python
Classifier: Programming Language :: Python :: 3.6
Classifier: Programming Language :: Python :: 3.7
Classifier: Topic :: Software Development :: Libraries
Requires-Dist: fastapi
Requires-Dist: uvicorn
Requires-Dist: ltp
Requires-Dist: pydantic
Requires-Dist: fire
Requires-Dist: httpx
Requires-Dist: PyYAML
